AUTHORS
ChangeLog
Readme.rst
requirements.txt
setup.cfg
setup.py
cursed_desktop/__init__.py
cursed_desktop/tui.py
cursed_desktop.egg-info/PKG-INFO
cursed_desktop.egg-info/SOURCES.txt
cursed_desktop.egg-info/dependency_links.txt
cursed_desktop.egg-info/entry_points.txt
cursed_desktop.egg-info/not-zip-safe
cursed_desktop.egg-info/pbr.json
cursed_desktop.egg-info/requires.txt
cursed_desktop.egg-info/top_level.txt
docs/Readme.rst
docs/cursedxdg.png