Metadata-Version: 1.1
Name: cursed-desktop
Version: 0.0.6.dev1
Summary: Ncurses menu using the freedesktop desktop entry spec
Home-page: http://github.com/XayOn/cursed_desktop
Author: David Francos Cuartero
Author-email: opensource@davidfrancos.net
License: GPL3+
Keywords: freedesktop
Platform: UNKNOWN
Classifier: Development Status :: 4 - Beta
Classifier: Environment :: Console
Classifier: Intended Audience :: Information Technology
Classifier: License :: OSI Approved :: GNU General Public License v3 (GPLv3)
Classifier: Operating System :: OS Independent
Classifier: Programming Language :: Python
